MANIFEST.in
acquirer_view.xml
portal_data.xml
portal_demo.xml
portal_view.xml
setup.py
./__init__.py
./__openerp__.py
./acquirer.py
./mail_mail.py
./mail_message.py
./portal.py
./tests/__init__.py
./tests/test_portal.py
./wizard/__init__.py
./wizard/portal_wizard.py
./wizard/share_wizard.py
i18n/ar.po
i18n/bg.po
i18n/bs.po
i18n/ca.po
i18n/cs.po
i18n/da.po
i18n/de.po
i18n/en_US.po
i18n/es.po
i18n/es_CR.po
i18n/es_MX.po
i18n/es_VE.po
i18n/et.po
i18n/fi.po
i18n/fr.po
i18n/he.po
i18n/hr.po
i18n/hu.po
i18n/id.po
i18n/it.po
i18n/ja.po
i18n/ko.po
i18n/lo.po
i18n/lt.po
i18n/mk.po
i18n/mn.po
i18n/nl.po
i18n/pl.po
i18n/portal.pot
i18n/pt.po
i18n/pt_BR.po
i18n/ro.po
i18n/ru.po
i18n/sl.po
i18n/sr.po
i18n/sv.po
i18n/th.po
i18n/tr.po
i18n/uk.po
i18n/zh_CN.po
i18n/zh_TW.po
openerp_portal.egg-info/PKG-INFO
openerp_portal.egg-info/SOURCES.txt
openerp_portal.egg-info/dependency_links.txt
openerp_portal.egg-info/requires.txt
openerp_portal.egg-info/top_level.txt
security/ir.model.access.csv
security/portal_security.xml
static/src/img/icon.png
wizard/portal_wizard_view.xml
wizard/share_wizard_view.xml